python_executor/__init__.py
python_executor/main.py
python_executor/requirements.txt
python_executor/server.py
python_executor/utils.py
webhook_bridge/__init__.py
webhook_bridge/__version__.py
webhook_bridge/cli.py
webhook_bridge-3.1.1.dist-info/LICENSE
webhook_bridge-3.1.1.dist-info/METADATA
webhook_bridge-3.1.1.dist-info/WHEEL
webhook_bridge-3.1.1.dist-info/entry_points.txt
webhook_bridge-3.1.1.dist-info/RECORD
