Metadata-Version: 2.3
Name: webhook-bridge
Version: 3.1.1
Summary: A flexible webhook integration platform with hybrid Go/Python architecture
License: MIT
Keywords: webhook,integration,platform,go,python
Author: hal.long
Author-email: hal.long@outlook.com
Requires-Python: >=3.8
Classifier: Development Status :: 5 - Production/Stable
Classifier: Intended Audience :: Developers
Classifier: License :: OSI Approved :: MIT License
Classifier: Operating System :: OS Independent
Classifier: Programming Language :: Python :: 3
Classifier: Programming Language :: Python :: 3.8
Classifier: Programming Language :: Python :: 3.9
Classifier: Programming Language :: Python :: 3.10
Classifier: Programming Language :: Python :: 3.11
Classifier: Programming Language :: Python :: 3.12
Requires-Dist: grpcio (>=1.50.0)
Requires-Dist: grpcio-tools (>=1.50.0)
Requires-Dist: pyyaml (>=6.0)
Project-URL: Documentation, https://github.com/loonghao/webhook_bridge#readme
Project-URL: Homepage, https://github.com/loonghao/webhook_bridge
Project-URL: Issues, https://github.com/loonghao/webhook_bridge/issues
Project-URL: Repository, https://github.com/loonghao/webhook_bridge
